actionlib_msgs/_dummy.cpython-313-x86_64-linux-gnu.so
ros_actionlib_msgs-5.5.1.data/data/include/actionlib_msgs/actionlib_msgs/msg/goal_id.h
ros_actionlib_msgs-5.5.1.data/data/include/actionlib_msgs/actionlib_msgs/msg/goal_id.hpp
ros_actionlib_msgs-5.5.1.data/data/include/actionlib_msgs/actionlib_msgs/msg/goal_status.h
ros_actionlib_msgs-5.5.1.data/data/include/actionlib_msgs/actionlib_msgs/msg/goal_status.hpp
ros_actionlib_msgs-5.5.1.data/data/include/actionlib_msgs/actionlib_msgs/msg/goal_status_array.h
ros_actionlib_msgs-5.5.1.data/data/include/actionlib_msgs/actionlib_msgs/msg/goal_status_array.hpp
ros_actionlib_msgs-5.5.1.data/data/include/actionlib_msgs/actionlib_msgs/msg/rosidl_generator_c__visibility_control.h
ros_actionlib_msgs-5.5.1.data/data/include/actionlib_msgs/actionlib_msgs/msg/rosidl_generator_cpp__visibility_control.hpp
ros_actionlib_msgs-5.5.1.data/data/include/actionlib_msgs/actionlib_msgs/msg/rosidl_typesupport_fastrtps_c__visibility_control.h
ros_actionlib_msgs-5.5.1.data/data/include/actionlib_msgs/actionlib_msgs/msg/rosidl_typesupport_fastrtps_cpp__visibility_control.h
ros_actionlib_msgs-5.5.1.data/data/include/actionlib_msgs/actionlib_msgs/msg/rosidl_typesupport_introspection_c__visibility_control.h
ros_actionlib_msgs-5.5.1.data/data/include/actionlib_msgs/actionlib_msgs/msg/detail/goal_id__builder.hpp
ros_actionlib_msgs-5.5.1.data/data/include/actionlib_msgs/actionlib_msgs/msg/detail/goal_id__description.c
ros_actionlib_msgs-5.5.1.data/data/include/actionlib_msgs/actionlib_msgs/msg/detail/goal_id__functions.c
ros_actionlib_msgs-5.5.1.data/data/include/actionlib_msgs/actionlib_msgs/msg/detail/goal_id__functions.h
ros_actionlib_msgs-5.5.1.data/data/include/actionlib_msgs/actionlib_msgs/msg/detail/goal_id__rosidl_typesupport_fastrtps_c.h
ros_actionlib_msgs-5.5.1.data/data/include/actionlib_msgs/actionlib_msgs/msg/detail/goal_id__rosidl_typesupport_fastrtps_cpp.hpp
ros_actionlib_msgs-5.5.1.data/data/lib/python3.13/site-packages/actionlib_msgs-5.5.1-py3.13.egg-info/PKG-INFO
ros_actionlib_msgs-5.5.1.data/data/lib/python3.13/site-packages/actionlib_msgs-5.5.1-py3.13.egg-info/SOURCES.txt
ros_actionlib_msgs-5.5.1.data/data/lib/python3.13/site-packages/actionlib_msgs-5.5.1-py3.13.egg-info/dependency_links.txt
ros_actionlib_msgs-5.5.1.data/data/lib/python3.13/site-packages/actionlib_msgs-5.5.1-py3.13.egg-info/top_level.txt
ros_actionlib_msgs-5.5.1.dist-info/METADATA
ros_actionlib_msgs-5.5.1.dist-info/WHEEL
ros_actionlib_msgs-5.5.1.dist-info/top_level.txt
ros_actionlib_msgs-5.5.1.dist-info/RECORD
ros_actionlib_msgs-5.5.1.dist-info/licenses/LICENSE
