Metadata-Version: 2.4
Name: ros-actionlib-msgs
Version: 5.5.1
Summary: This deprecated ROS 1 package, actionlib_msgs, supports bridging ROS 1 action topics.
License-File: LICENSE
Requires-Dist: ros-rosidl-default-runtime~=1.7.1
Requires-Dist: ros-builtin-interfaces~=2.3.0
Requires-Dist: ros-std-msgs~=5.5.1
Dynamic: description
Dynamic: description-content-type
Dynamic: license-file
Dynamic: requires-dist
Dynamic: summary
